{
  "obsidian-git:commit": [
    {
      "modifiers": [
        "Mod",
        "Shift"
      ],
      "key": "C"
    }
  ],
  "obsidian-git:push2": [
    {
      "modifiers": [
        "Mod",
        "Shift"
      ],
      "key": "P"
    }
  ],
  "obsidian-git:pull": [
    {
      "modifiers": [
        "Mod",
        "Shift"
      ],
      "key": "["
    }
  ],
  "app:go-back": [
    {
      "modifiers": [
        "Mod",
        "Alt"
      ],
      "key": "ArrowLeft"
    },
    {
      "modifiers": [
        "Mod"
      ],
      "key": "Z"
    }
  ],
  "editor:toggle-spellcheck": [
    {
      "modifiers": [
        "Mod"
      ],
      "key": "A"
    }
  ],
  "editor:insert-horizontal-rule": [
    {
      "modifiers": [
        "Mod"
      ],
      "key": "Q"
    }
  ],
  "editor:toggle-strikethrough": [
    {
      "modifiers": [
        "Mod"
      ],
      "key": "Y"
    }
  ],
  "cmenu-plugin:hide-show-menu": [
    {
      "modifiers": [
        "Mod"
      ],
      "key": "M"
    }
  ]
}